pyrfidgeek/__init__.py
pyrfidgeek/crc.py
pyrfidgeek/rfidgeek.py
rfidgeek/__init__.py
rfidgeek/crc.py
rfidgeek/rfidgeek.py
rfidgeek-2.0.1.dist-info/DESCRIPTION.rst
rfidgeek-2.0.1.dist-info/METADATA
rfidgeek-2.0.1.dist-info/RECORD
rfidgeek-2.0.1.dist-info/WHEEL
rfidgeek-2.0.1.dist-info/metadata.json
rfidgeek-2.0.1.dist-info/top_level.txt
