Metadata-Version: 2.0
Name: rfidgeek
Version: 2.0.1
Summary: Read/write ISO 15693 cards following the Danish RFID data model for libraries
Home-page: https://github.com/scriptotek/pyrfidgeek
Author: Dan Michael O. Heggø
Author-email: d.m.heggo@ub.uio.no
License: MIT
Keywords: rfid iso15693 iso14443 libdev
Platform: UNKNOWN
Classifier: Intended Audience :: Developers
Classifier: License :: OSI Approved :: MIT License
Classifier: Programming Language :: Python :: 2
Classifier: Programming Language :: Python :: 2.7
Classifier: Programming Language :: Python :: 3
Classifier: Programming Language :: Python :: 3.3
Classifier: Programming Language :: Python :: 3.4
Classifier: Programming Language :: Python :: 3.5
Requires-Dist: pyserial
